[
	{
		"command": "account.Rename",
		"chain": "authdWrite",
		"ctor": ["Account","Title"],
		"crudNature": "update",
		"title": "Rename account",
		"fields": [
			{ "key": "Account", "hideIfDefaultValue": true },
			{ "key": "Title" }
		]
	},
	{
		"command": "account.Move",
		"chain": "authdWrite",
		"ctor": ["Account"],
		"crudNature": "update",
		"title": "Move account to different folder",
		"fields": [
			{ "key": "Account", "hideIfDefaultValue": true },
			{ "key": "NewParentFolder" }
		]
	},
	{
		"command": "account.ChangeUsername",
		"chain": "authdWrite",
		"ctor": ["Account","Username"],
		"crudNature": "update",
		"title": "Change username",
		"fields": [
			{ "key": "Account", "hideIfDefaultValue": true },
			{ "key": "Username" }
		]
	},
	{
		"command": "account.ChangeDescription",
		"chain": "authdWrite",
		"ctor": ["Account","Description"],
		"crudNature": "update",
		"title": "Change description",
		"fields": [
			{ "key": "Account", "hideIfDefaultValue": true },
			{ "key": "Description", "type": "multiline", "optional": true }
		]
	},
	{
		"command": "account.ChangeUrl",
		"chain": "authdWrite",
		"ctor": ["Account","Url"],
		"crudNature": "update",
		"title": "Change URL",
		"fields": [
			{ "key": "Account", "hideIfDefaultValue": true },
			{ "key": "Url", "optional": true }
		]
	},
	{
		"command": "account.DeleteSecret",
		"chain": "authdWrite",
		"ctor": ["Account","Secret"],
		"crudNature": "delete",
		"title": "Delete secret",
		"fields": [
			{ "key": "Account", "hideIfDefaultValue": true },
			{ "key": "Secret", "hideIfDefaultValue": true }
		]
	},
	{
		"command": "account.CreateFolder",
		"chain": "authdWrite",
		"ctor": ["Parent"],
		"crudNature": "create",
		"title": "+ Folder",
		"fields": [
			{ "key": "Parent", "hideIfDefaultValue": true },
			{ "key": "Name" }
		]
	},
	{
		"command": "account.DeleteFolder",
		"chain": "authdWrite",
		"ctor": ["Id"],
		"crudNature": "delete",
		"title": "Delete folder",
		"fields": [
			{ "key": "Id", "hideIfDefaultValue": true }
		]
	},
	{
		"command": "account.RenameFolder",
		"chain": "authdWrite",
		"ctor": ["Id","Name"],
		"crudNature": "update",
		"title": "Rename",
		"fields": [
			{ "key": "Id", "hideIfDefaultValue": true },
			{ "key": "Name" }
		]
	},
	{
		"command": "account.MoveFolder",
		"chain": "authdWrite",
		"ctor": ["Id"],
		"crudNature": "update",
		"title": "Move",
		"fields": [
			{ "key": "Id", "hideIfDefaultValue": true },
			{ "key": "NewParent" }
		]
	},
	{
		"command": "account.Create",
		"chain": "authdWrite",
		"ctor": ["FolderId"],
		"crudNature": "create",
		"title": "+ Account",
		"fields": [
			{ "key": "FolderId", "hideIfDefaultValue": true },
			{ "key": "Title", "optional": true, "help": "If you don`t specify this, then URL is required" },
			{ "key": "Url", "optional": true, "help": "If you don`t specify this, then Title is required" },
			{ "key": "Username", "optional": true },
			{ "key": "Password", "type": "password", "optional": true },
			{ "key": "PasswordRepeat", "type": "password", "optional": true }
		]
	},
	{
		"command": "account.Delete",
		"chain": "authdWrite",
		"ctor": ["Id"],
		"crudNature": "delete",
		"title": "Delete",
		"additional_confirmation": "Are you sure?",
		"fields": [
			{ "key": "Id", "hideIfDefaultValue": true }
		]
	},
	{
		"command": "account.AddPassword",
		"chain": "authdWrite",
		"ctor": ["Account"],
		"crudNature": "create",
		"title": "+ Password",
		"fields": [
			{ "key": "Account", "hideIfDefaultValue": true },
			{ "key": "Password", "type": "password", "help": "Enter \"_auto\" to autogenerate one" },
			{ "key": "PasswordRepeat", "type": "password" }
		]
	},
	{
		"command": "account.AddKeylist",
		"chain": "authdWrite",
		"ctor": ["Account"],
		"crudNature": "create",
		"title": "+ Keylist",
		"fields": [
			{ "key": "Account", "hideIfDefaultValue": true },
			{ "key": "Title" },
			{ "key": "ExpectedKeyCount", "type": "integer" },
			{ "key": "LengthOfKeys", "type": "integer" },
			{ "key": "LengthOfValues", "type": "integer" },
			{ "key": "Keylist", "type": "multiline" }
		]
	},
	{
		"command": "account.AddSshKey",
		"chain": "authdWrite",
		"ctor": ["Id"],
		"crudNature": "create",
		"title": "+ SSH key",
		"fields": [
			{ "key": "Id", "hideIfDefaultValue": true },
			{ "key": "SshPrivateKey", "type": "multiline" }
		]
	},
	{
		"command": "account.AddSecretNote",
		"chain": "authdWrite",
		"ctor": ["Account"],
		"crudNature": "create",
		"title": "+ Secret note",
		"fields": [
			{ "key": "Account", "hideIfDefaultValue": true },
			{ "key": "Title" },
			{ "key": "Note", "type": "multiline" }
		]
	},
	{
		"command": "account.AddOtpToken",
		"chain": "authdWrite",
		"ctor": ["Account","OtpProvisioningUrl"],
		"crudNature": "create",
		"title": "Add OTP token",
		"fields": [
			{ "key": "Account", "hideIfDefaultValue": true },
			{ "key": "OtpProvisioningUrl" }
		]
	},
	{
		"command": "database.ChangeMasterPassword",
		"chain": "authdWrite",
		"ctor": [],
		"crudNature": "update",
		"title": "Change master password",
		"fields": [
			{ "key": "NewMasterPassword", "type": "password" },
			{ "key": "NewMasterPasswordRepeat", "type": "password" }
		]
	},
	{
		"command": "session.SignIn",
		"chain": "public",
		"ctor": ["Username"],
		"crudNature": "update",
		"title": "Sign in",
		"fields": [
			{ "key": "Username", "hideIfDefaultValue": true },
			{ "key": "Password", "type": "password" }
		]
	},
	{
		"command": "session.SignOut",
		"chain": "authdWrite",
		"ctor": [],
		"crudNature": "update",
		"title": "Sign out",
		"fields": []
	},
	{
		"command": "database.Unseal",
		"chain": "public",
		"ctor": [],
		"crudNature": "update",
		"title": "Unseal database",
		"fields": [
			{ "key": "MasterPassword", "type": "password" }
		]
	},
	{
		"command": "database.ExportToKeepass",
		"chain": "authdWrite",
		"ctor": [],
		"crudNature": "update",
		"title": "Export to KeePass format",
		"fields": []
	},
	{
		"command": "user.Create",
		"chain": "authdWrite",
		"ctor": [],
		"crudNature": "create",
		"title": "+ User",
		"fields": [
			{ "key": "Username", "validation_regex": "^[a-zA-Z0-9@_\\-]+$", "help": "a-z, A-Z, 0-9, _ and -" },
			{ "key": "Password", "type": "password" },
			{ "key": "PasswordRepeat", "type": "password" }
		]
	},
	{
		"command": "user.ChangePassword",
		"chain": "authdWrite",
		"ctor": ["User"],
		"crudNature": "update",
		"title": "Change password",
		"fields": [
			{ "key": "User", "hideIfDefaultValue": true },
			{ "key": "Password", "type": "password" },
			{ "key": "PasswordRepeat", "type": "password" }
		]
	},
	{
		"command": "user.RegisterU2FToken",
		"chain": "authdWrite",
		"ctor": ["Request"],
		"crudNature": "create",
		"title": "Register U2F token",
		"fields": [
			{ "key": "Request" },
			{ "key": "Name" }
		]
	}
]
